easySemanticSearch/__init__.py
easySemanticSearch/main.py
easySemanticSearch-1.3.3.dist-info/METADATA
easySemanticSearch-1.3.3.dist-info/WHEEL
easySemanticSearch-1.3.3.dist-info/top_level.txt
easySemanticSearch-1.3.3.dist-info/RECORD
