Metadata-Version: 2.1
Name: easySemanticSearch
Version: 1.3.3
Summary: UserFriendly implementation of Highly optimized advanced semantic search.
Author: Abhishek Venkatachalam
Author-email: abhishek.venkatachalam06@gmail.com
Classifier: Programming Language :: Python :: 3
Classifier: License :: OSI Approved :: MIT License
Classifier: Operating System :: OS Independent
Requires-Python: >=3.8
Requires-Dist: sentence-transformers
Requires-Dist: numpy
Requires-Dist: pandas
